easy_login/__init__.py
easy_login/admin.py
easy_login/apps.py
easy_login/context_processors.py
easy_login/forms.py
easy_login/models.py
easy_login/tests.py
easy_login/urls.py
easy_login/views.py
easy_login/migrations/__init__.py
easy_login/static/easy_login/css/main.css
easy_login/static/easy_login/icons/user.svg
easy_login/static/easy_login/js/easy-login.js
easy_login/templates/easy_login_form.html
django_easy_login-0.1.dev2.dist-info/LICENSE
django_easy_login-0.1.dev2.dist-info/METADATA
django_easy_login-0.1.dev2.dist-info/WHEEL
django_easy_login-0.1.dev2.dist-info/top_level.txt
django_easy_login-0.1.dev2.dist-info/RECORD
